pytorch_replay/__init__.py
pytorch_replay/__main__.py
pytorch_replay_narsil-0.0.1.dist-info/LICENSE
pytorch_replay_narsil-0.0.1.dist-info/METADATA
pytorch_replay_narsil-0.0.1.dist-info/WHEEL
pytorch_replay_narsil-0.0.1.dist-info/top_level.txt
pytorch_replay_narsil-0.0.1.dist-info/RECORD
