Metadata-Version: 2.1
Name: pytorch-replay-narsil
Version: 0.0.1
Summary: Make running, replaying experiments packaging models easier
Home-page: https://github.com/Narsil/pytorch_replay
Author: Nicolas Patry
Author-email: patry.nicolas@gmail.com
License: UNKNOWN
Platform: UNKNOWN
Classifier: Programming Language :: Python :: 3
Classifier: License :: OSI Approved :: MIT License
Classifier: Operating System :: OS Independent
